packtrack/__init__.py
packtrack/apps.py
packtrack/serializers.py
packtrack/urls.py
packtrack/utils.py
packtrack/views.py
packtrack/admin/__init__.py
packtrack/admin/outdated_packages.py
packtrack/admin/package_caches.py
packtrack/admin/update_logs.py
packtrack/admin/__pycache__/__init__.cpython-312.pyc
packtrack/admin/__pycache__/outdated_packages.cpython-312.pyc
packtrack/admin/__pycache__/package_caches.cpython-312.pyc
packtrack/admin/__pycache__/update_logs.cpython-312.pyc
packtrack/management/.DS_Store
packtrack/management/__init__.py
packtrack/management/__pycache__/__init__.cpython-312.pyc
packtrack/management/commands/.DS_Store
packtrack/management/commands/__init__.py
packtrack/management/commands/update_package.py
packtrack/management/commands/__pycache__/__init__.cpython-312.pyc
packtrack/management/commands/__pycache__/update_outdated_packages_list.cpython-312.pyc
packtrack/management/commands/__pycache__/update_package.cpython-312.pyc
packtrack/migrations/0001_initial.py
packtrack/migrations/0002_updatelog.py
packtrack/migrations/__init__.py
packtrack/migrations/__pycache__/0001_initial.cpython-312.pyc
packtrack/migrations/__pycache__/0002_updatelog.cpython-312.pyc
packtrack/migrations/__pycache__/__init__.cpython-312.pyc
packtrack/models/__init__.py
packtrack/models/outdated_package.py
packtrack/models/package_cache.py
packtrack/models/update_log.py
packtrack/models/__pycache__/__init__.cpython-312.pyc
packtrack/models/__pycache__/outdated_package.cpython-312.pyc
packtrack/models/__pycache__/package_cache.cpython-312.pyc
packtrack/models/__pycache__/update_log.cpython-312.pyc
packtrack/templates/packtrack/admin/outdated_packages_change_list.html
packtrack/tests/test_utils.py
packtrack/tests/__pycache__/test_utils.cpython-312-pytest-8.2.2.pyc
packtrack/tests/__pycache__/test_utils.cpython-312.pyc
django_packtrack-24.12.1.dist-info/METADATA
django_packtrack-24.12.1.dist-info/WHEEL
django_packtrack-24.12.1.dist-info/top_level.txt
django_packtrack-24.12.1.dist-info/RECORD
