Metadata-Version: 2.1
Name: django-packtrack
Version: 24.12.1
Summary: A Django app for monitoring outdated packages and dependencies.
Author-email: Grzegorz Krol <grze.krol@proton.me>
License: MIT
Project-URL: homepage, https://github.com/cjkpl/django-packtrack
Project-URL: repository, https://github.com/cjkpl/django-packtrack
Keywords: django,package,monitor,dependencies
Classifier: Development Status :: 4 - Beta
Classifier: Framework :: Django
Classifier: Framework :: Django :: 5.0
Classifier: License :: OSI Approved :: MIT License
Classifier: Programming Language :: Python
Classifier: Programming Language :: Python :: 3
Requires-Dist: django>=5.0
Requires-Dist: requests>=2.0
Requires-Dist: djangorestframework
Requires-Dist: djangorestframework-simplejwt
